LICENSE
MANIFEST.in
README.md
setup.py
twint_cn/__init__.py
twint_cn/__version__.py
twint_cn/cli.py
twint_cn/config.py
twint_cn/datelock.py
twint_cn/feed.py
twint_cn/format.py
twint_cn/get.py
twint_cn/output.py
twint_cn/run.py
twint_cn/tweet.py
twint_cn/url.py
twint_cn/user.py
twint_cn/verbose.py
twint_cn.egg-info/PKG-INFO
twint_cn.egg-info/SOURCES.txt
twint_cn.egg-info/dependency_links.txt
twint_cn.egg-info/entry_points.txt
twint_cn.egg-info/requires.txt
twint_cn.egg-info/top_level.txt
twint_cn/storage/__init__.py
twint_cn/storage/db.py
twint_cn/storage/elasticsearch.py
twint_cn/storage/panda.py
twint_cn/storage/write.py
twint_cn/storage/write_meta.py