Metadata-Version: 2.1
Name: twint-cn
Version: 2.1.15
Summary: An advanced Twitter scraping & OSINT tool.
Home-page: https://github.com/twintproject/twint
Author: Cody Zacharias
Author-email: codyzacharias@pm.me
License: MIT
Platform: UNKNOWN
Classifier: License :: OSI Approved :: MIT License
Classifier: Programming Language :: Python
Classifier: Programming Language :: Python :: 3
Classifier: Programming Language :: Python :: 3.6
Classifier: Programming Language :: Python :: 3.7
Classifier: Programming Language :: Python :: 3.8
Classifier: Programming Language :: Python :: Implementation :: CPython
Requires-Python: >=3.6.0
